jamfpy/__init__.py
jamfpy/client/__init__.py
jamfpy/client/api.py
jamfpy/client/auth.py
jamfpy/client/client.py
jamfpy/client/constants.py
jamfpy/client/exceptions.py
jamfpy/client/http_config.py
jamfpy/client/logger.py
jamfpy/client/tenant.py
jamfpy/client/utility.py
jamfpy/endpoints/__init__.py
jamfpy/endpoints/clc_endpoints.py
jamfpy/endpoints/clc_endpoints_accounts.py
jamfpy/endpoints/models.py
jamfpy/endpoints/pro_app_installers.py
jamfpy/endpoints/pro_mdm_commands.py
jamfpy/endpoints/pro_scripts.py
jamfpy-2.6.0.dist-info/METADATA
jamfpy-2.6.0.dist-info/WHEEL
jamfpy-2.6.0.dist-info/entry_points.txt
jamfpy-2.6.0.dist-info/top_level.txt
jamfpy-2.6.0.dist-info/RECORD
