Metadata-Version: 2.4
Name: jamfpy
Version: 2.6.0
Author: Joseph Little
Requires-Python: >=3.8
Requires-Dist: requests
Provides-Extra: pdf
Requires-Dist: ReportLab>=1.2; extra == "pdf"
Requires-Dist: RXP; extra == "pdf"
Provides-Extra: rest
Requires-Dist: docutils>=0.3; extra == "rest"
Requires-Dist: pack==1.1,==1.3; extra == "rest"
